PyOMWeather/__init__.py
PyOMWeather/weather.py
PyOMWeather-0.1.0.dist-info/LICENSE
PyOMWeather-0.1.0.dist-info/METADATA
PyOMWeather-0.1.0.dist-info/WHEEL
PyOMWeather-0.1.0.dist-info/top_level.txt
PyOMWeather-0.1.0.dist-info/RECORD
