Metadata-Version: 2.1
Name: PyOMWeather
Version: 0.1.0
Summary: A small weather package using Open-Meteo
Author-email: Alessandro Landi <al6723@nyu.edu>, Geoffrey Budiman <gkb8774@nyu.edu>, Nawaf Alabdullah <na2746@nyu.edu>, Shreyas Ujagar <su2043@nyu.edu>
Project-URL: Homepage, https://github.com/software-students-fall2023/3-python-package-exercise-team1-pt3
Classifier: Programming Language :: Python :: 3
Classifier: License :: OSI Approved :: MIT License
Classifier: Operating System :: OS Independent
Requires-Python: >=3.7
License-File: LICENSE
Requires-Dist: requests-cache
Requires-Dist: requests
Requires-Dist: pandas
Requires-Dist: geopy
Requires-Dist: openmeteo-requests
Requires-Dist: retry-requests
Provides-Extra: dev
Requires-Dist: pytest ; extra == 'dev'
Requires-Dist: build ; extra == 'dev'
Requires-Dist: twine ; extra == 'dev'
